dtech_password_generator/__init__.py
dtech_password_generator/passgen.py
dtech_password_generator-1.0.0.dist-info/LICENSE
dtech_password_generator-1.0.0.dist-info/METADATA
dtech_password_generator-1.0.0.dist-info/WHEEL
dtech_password_generator-1.0.0.dist-info/top_level.txt
dtech_password_generator-1.0.0.dist-info/RECORD
