Metadata-Version: 2.1
Name: dtech-password-generator
Version: 1.0.0
Summary: A simple password generator package.
Home-page: UNKNOWN
Author: Daniel Wangari
Author-email: danielnjama2015@gmail.com
License: MIT
Platform: UNKNOWN
Classifier: Programming Language :: Python :: 3
Classifier: License :: OSI Approved :: MIT License
Classifier: Operating System :: OS Independent
Requires-Python: >=3.6
